UzSonSoz/UzSonSoz.py
UzSonSoz/__init__.py
UzSonSoz-1.0.dist-info/LICENSE.txt
UzSonSoz-1.0.dist-info/METADATA
UzSonSoz-1.0.dist-info/WHEEL
UzSonSoz-1.0.dist-info/top_level.txt
UzSonSoz-1.0.dist-info/RECORD
