Metadata-Version: 2.1
Name: UzSonSoz
Version: 1.0
Summary: O‘zbek tilida sonlarni so‘zga, so‘zlarni esa songa almashtiruvchi dastur.
Home-page: https://github.com/ddasturbek/UzSonSoz
Author: dasturbek
Author-email: sobirovogabek0409@gmail.com
Classifier: Programming Language :: Python :: 3
Classifier: License :: OSI Approved :: MIT License
Classifier: Operating System :: OS Independent
Requires-Python: >=3.6
License-File: LICENSE.txt
